scirs2/__init__.py
scirs2/__init__.pyi
scirs2/py.typed
scirs2/scirs2.cpython-313-darwin.so
scirs2-0.1.3.dist-info/METADATA
scirs2-0.1.3.dist-info/WHEEL
scirs2.pyi
scirs2-0.1.3.dist-info/RECORD
