Metadata-Version: 2.4
Name: scirs2
Version: 0.1.3
Classifier: Development Status :: 4 - Beta
Classifier: Intended Audience :: Science/Research
Classifier: Intended Audience :: Developers
Classifier: License :: OSI Approved :: MIT License
Classifier: License :: OSI Approved :: Apache Software License
Classifier: Programming Language :: Rust
Classifier: Programming Language :: Python :: 3
Classifier: Programming Language :: Python :: 3.8
Classifier: Programming Language :: Python :: 3.9
Classifier: Programming Language :: Python :: 3.10
Classifier: Programming Language :: Python :: 3.11
Classifier: Programming Language :: Python :: 3.12
Classifier: Programming Language :: Python :: 3.13
Classifier: Topic :: Scientific/Engineering
Classifier: Topic :: Scientific/Engineering :: Mathematics
Classifier: Topic :: Software Development :: Libraries :: Python Modules
Requires-Dist: numpy>=1.20.0
Requires-Dist: pytest>=7.0 ; extra == 'dev'
Requires-Dist: pandas>=1.0 ; extra == 'dev'
Requires-Dist: scipy>=1.7 ; extra == 'dev'
Provides-Extra: dev
Summary: SciRS2: A comprehensive scientific computing library in Rust - Python bindings (SciPy alternative)
Keywords: scientific,numpy,scipy,machine-learning,statistics
Home-Page: https://github.com/cool-japan/scirs
Author-email: COOLJAPAN OU <contact@cooljapan.tech>
License: MIT OR Apache-2.0
Requires-Python: >=3.8
Project-URL: Bug Tracker, https://github.com/cool-japan/scirs/issues
Project-URL: Documentation, https://docs.rs/scirs2
Project-URL: Homepage, https://github.com/cool-japan/scirs
Project-URL: Repository, https://github.com/cool-japan/scirs
